upsolver/__init__.py
upsolver/client/__init__.py
upsolver/client/auth_filler.py
upsolver/client/exceptions.py
upsolver/client/poller.py
upsolver/client/query.py
upsolver/client/requester.py
upsolver/client/response.py
upsolver/dbapi/README.md
upsolver/dbapi/__init__.py
upsolver/dbapi/connection.py
upsolver/dbapi/cursor.py
upsolver/dbapi/examples.py
upsolver/dbapi/type_constructors.py
upsolver/dbapi/types_definitions.py
upsolver/dbapi/utils.py
upsolver/sdk/__init__.py
upsolver/sdk/client.py
upsolver/sdk/utils.py
upsolver/utils.py
upsolver_sdk_python-0.1.12.dist-info/METADATA
upsolver_sdk_python-0.1.12.dist-info/WHEEL
upsolver_sdk_python-0.1.12.dist-info/RECORD
