Metadata-Version: 2.1
Name: upsolver-sdk-python
Version: 0.1.12
Summary: Python SDK for Upsolver
License: MIT
Author: Upsolver Team
Author-email: info@upsolver.com
Requires-Python: >=3.7,<4.0
Classifier: License :: OSI Approved :: MIT License
Classifier: Programming Language :: Python :: 3
Classifier: Programming Language :: Python :: 3.7
Classifier: Programming Language :: Python :: 3.8
Classifier: Programming Language :: Python :: 3.9
Classifier: Programming Language :: Python :: 3.10
Classifier: Programming Language :: Python :: 3.11
Classifier: Programming Language :: Python :: 3.12
Requires-Dist: requests (>=2.31.0,<3.0.0)
Requires-Dist: yarl (>=1.8.2,<2.0.0)
